libfp/__init__.py
libfp/_fplib.cpython-310-darwin.so
libfp/_libfp.cpython-310-darwin.so
libfp/libfp.py
libfp-3.1.3.dist-info/licenses/LICENSE
libfp-3.1.3.dist-info/METADATA
libfp-3.1.3.dist-info/WHEEL
libfp-3.1.3.dist-info/top_level.txt
libfp-3.1.3.dist-info/RECORD
