Metadata-Version: 2.4
Name: libfp
Version: 3.1.3
Summary: This is the libfp module.
Author-email: Zhu Research Group <li.zhu@rutgers.edu>
License: MIT
Project-URL: Homepage, https://github.com/Rutgers-ZRG/libfp
Classifier: License :: OSI Approved :: MIT License
Classifier: Programming Language :: Python :: 3
License-File: LICENSE
Requires-Dist: numpy
Dynamic: license-file
